fileloghelper/__init__.py
fileloghelper-1.7.1.dist-info/LICENSE
fileloghelper-1.7.1.dist-info/METADATA
fileloghelper-1.7.1.dist-info/WHEEL
fileloghelper-1.7.1.dist-info/top_level.txt
fileloghelper-1.7.1.dist-info/RECORD
