Metadata-Version: 2.1
Name: fileloghelper
Version: 1.7.1
Summary: Helper for logging to files
Home-page: https://github.com/mithem/filelog
Author: mithem
Author-email: miguel.themann@gmail.com
License: UNKNOWN
Platform: UNKNOWN
Classifier: Programming Language :: Python :: 3
Classifier: License :: OSI Approved :: MIT License
Classifier: Operating System :: OS Independent
Requires-Python: >=3.6
